{
    "version": "2025-12-02-72dbcf1",
    "description": "Video player based on MPlayer/mplayer2 (builds by zhongfly)",
    "homepage": "https://mpv.io",
    "license": "LGPL-2.1-or-later,GPL-2.0-or-later",
    "notes": [
        "To set and unset file type associations and AutoPlay handlers, run '$dir\\installer\\mpv-install.bat' and '$dir\\installer\\mpv-uninstall.bat' as administrator, respectively.",
        "You can use Icaros ('nonportable/icaros-np') to enable thumbnails for all media types."
    ],
    "suggest": {
        "yt-dlp": "yt-dlp"
    },
    "architecture": {
        "64bit": {
            "url": "https://github.com/zhongfly/mpv-winbuild/releases/download/2025-12-02-72dbcf1/mpv-x86_64-v3-20251202-git-72dbcf1.7z",
            "hash": "fad21b59d62601359a1c0a8cdd4aeb1b24700c8af508110e3741794022f0c611"
        },
        "arm64": {
            "url": "https://github.com/zhongfly/mpv-winbuild/releases/download/2025-12-02-72dbcf1/mpv-aarch64-20251202-git-72dbcf1.7z",
            "hash": "a8533bdd27436a3e0421a49378d59b923f18b789f514eaeaae34f2b6e31a1096"
        }
    },
    "pre_install": "Remove-Item \"$dir\\updater.bat\"",
    "env_add_path": ".",
    "shortcuts": [
        [
            "mpv.exe",
            "mpv"
        ]
    ],
    "persist": "portable_config",
    "checkver": {
        "url": "https://api.github.com/repos/zhongfly/mpv-winbuild/releases/latest",
        "jsonpath": "$.assets..browser_download_url",
        "regex": "(\\d{4}-\\d{2}-\\d{2}-[\\da-f]+)/mpv-x86_64-v3-(?<date>\\d{8})-git-(?<commit>[\\da-f]+)\\.7z"
    },
    "autoupdate": {
        "architecture": {
            "64bit": {
                "url": "https://github.com/zhongfly/mpv-winbuild/releases/download/$version/mpv-x86_64-v3-$matchDate-git-$matchCommit.7z"
            },
            "arm64": {
                "url": "https://github.com/zhongfly/mpv-winbuild/releases/download/$version/mpv-aarch64-$matchDate-git-$matchCommit.7z"
            }
        }
    }
}
